LICENSE
opentelemetry_instrumentation_django_outbox_pattern/__init__.py
opentelemetry_instrumentation_django_outbox_pattern/instrumentors/__init__.py
opentelemetry_instrumentation_django_outbox_pattern/instrumentors/consumer_instrument.py
opentelemetry_instrumentation_django_outbox_pattern/instrumentors/publisher_instrument.py
opentelemetry_instrumentation_django_outbox_pattern/package.py
opentelemetry_instrumentation_django_outbox_pattern/utils/__init__.py
opentelemetry_instrumentation_django_outbox_pattern/utils/django_outbox_pattern_getter.py
opentelemetry_instrumentation_django_outbox_pattern/utils/formatters.py
opentelemetry_instrumentation_django_outbox_pattern/utils/shared_types.py
opentelemetry_instrumentation_django_outbox_pattern/utils/span.py
opentelemetry_instrumentation_django_outbox_pattern/utils/traced_thread_pool_executor.py
opentelemetry_instrumentation_django_outbox_pattern/version.py
opentelemetry_instrumentation_django_outbox_pattern-0.2.0.dist-info/LICENSE
opentelemetry_instrumentation_django_outbox_pattern-0.2.0.dist-info/METADATA
opentelemetry_instrumentation_django_outbox_pattern-0.2.0.dist-info/WHEEL
opentelemetry_instrumentation_django_outbox_pattern-0.2.0.dist-info/RECORD
