Metadata-Version: 2.1
Name: opentelemetry-instrumentation-django-outbox-pattern
Version: 0.2.0
Summary: Opentelemetry instrumentor for django-outbox-pattern package
Home-page: https://github.com/juntossomosmais/opentelemetry-instrumentation-django-outbox-pattern
License: MIT
Keywords: django-outbox-pattern,outbox-pattern,django,opentelemetry,instrumentation
Author: Juntos Somos Mais
Author-email: labs@juntossomosmais.com.br
Requires-Python: >=3.10,<4.0
Classifier: License :: OSI Approved :: MIT License
Classifier: Programming Language :: Python :: 3
Classifier: Programming Language :: Python :: 3.10
Classifier: Programming Language :: Python :: 3.11
Requires-Dist: Django
Requires-Dist: django-outbox-pattern (>=3.0.7,<4.0.0)
Requires-Dist: opentelemetry-api
Requires-Dist: opentelemetry-instrumentation
Requires-Dist: opentelemetry-sdk
Project-URL: Repository, https://github.com/juntossomosmais/opentelemetry-instrumentation-django-outbox-pattern
